grapycal_torch/__init__.py
grapycal_torch/activation.py
grapycal_torch/basic.py
grapycal_torch/cnn.py
grapycal_torch/configureNode.py
grapycal_torch/dataloader.py
grapycal_torch/generative.py
grapycal_torch/loss.py
grapycal_torch/manager.py
grapycal_torch/moduleNode.py
grapycal_torch/networkDef.py
grapycal_torch/normalize.py
grapycal_torch/optimizerNode.py
grapycal_torch/pyproject.toml
grapycal_torch/README.md
grapycal_torch/settings.py
grapycal_torch/tensor.py
grapycal_torch/tensor_operations.py
grapycal_torch/transform.py
grapycal_torch/utils.py
grapycal_torch-0.3.0.dist-info/METADATA
grapycal_torch-0.3.0.dist-info/WHEEL
grapycal_torch-0.3.0.dist-info/RECORD
