Metadata-Version: 2.1
Name: grapycal-torch
Version: 0.3.0
Summary: A Grapycal extension for PyTorch
License: BSD-3-Clause
Author: eri24816
Author-email: a931eric@gmail.com
Requires-Python: >=3.11,<4.0
Classifier: License :: OSI Approved :: BSD License
Classifier: Programming Language :: Python :: 3
Classifier: Programming Language :: Python :: 3.11
Requires-Dist: aiofiles (>=23.2.1,<24.0.0)
Requires-Dist: einops (>=0.7.0,<0.8.0)
Requires-Dist: grapycal (>=0.11.0)
Requires-Dist: torch (==2.*)
Requires-Dist: torchvision (>=0.16.1,<0.17.0)
